RBytes/RBytes.py
RBytes/__init__.py
RBytes-3.0.dist-info/METADATA
RBytes-3.0.dist-info/WHEEL
RBytes-3.0.dist-info/top_level.txt
RBytes-3.0.dist-info/RECORD
