Metadata-Version: 2.1
Name: RBytes
Version: 3.0
Summary: Library that allows you to work with arrays of bytes
Home-page: https://github.com/DoctorEenot/RBytes
Author: DrEenot
Author-email: dreenot@gmail.com
License: UNKNOWN
Platform: UNKNOWN
Classifier: Programming Language :: Python :: 3
Classifier: License :: OSI Approved :: MIT License
Classifier: Operating System :: OS Independent
